pyopenide_client/__init__.py
pyopenide_client/decorator_client.py
pyopenide_client/global_client.py
pyopenide_client/magic_client.py
pyopenide_client/simple_client.py
pyopenide_client/ultra_simple.py
pyopenide_client-1.1.2.dist-info/licenses/LICENSE
pyopenide_client-1.1.2.dist-info/METADATA
pyopenide_client-1.1.2.dist-info/WHEEL
pyopenide_client-1.1.2.dist-info/entry_points.txt
pyopenide_client-1.1.2.dist-info/top_level.txt
pyopenide_client-1.1.2.dist-info/RECORD
